smsedge_api_python/__init__.py
smsedge_api_python/sms_edge_api.py
smsedge_api_python_SMSEdge-2.0.1.dist-info/LICENSE.txt
smsedge_api_python_SMSEdge-2.0.1.dist-info/METADATA
smsedge_api_python_SMSEdge-2.0.1.dist-info/WHEEL
smsedge_api_python_SMSEdge-2.0.1.dist-info/top_level.txt
smsedge_api_python_SMSEdge-2.0.1.dist-info/RECORD
